{
  "version": "1",
  "cognitoConfig": {
    "resourceNameTruncated": "myrecif3d70b73",
    "userPoolName": "myrecipeslol_USERPOOL",
    "autoVerifiedAttributes": [
      "email"
    ],
    "mfaConfiguration": "OFF",
    "mfaTypes": [
      "SMS Text Message"
    ],
    "smsAuthenticationMessage": "Your authentication code is {####}",
    "smsVerificationMessage": "Your verification code is {####}",
    "emailVerificationSubject": "Your verification code",
    "emailVerificationMessage": "Your verification code is {####}",
    "defaultPasswordPolicy": false,
    "passwordPolicyMinLength": 8,
    "passwordPolicyCharacters": [],
    "requiredAttributes": [
      "email",
      "name"
    ],
    "aliasAttributes": [],
    "userpoolClientGenerateSecret": false,
    "userpoolClientRefreshTokenValidity": 30,
    "userpoolClientWriteAttributes": [
      "email",
      "name"
    ],
    "userpoolClientReadAttributes": [
      "email"
    ],
    "userpoolClientLambdaRole": "myrecif3d70b73_userpoolclient_lambda_role",
    "userpoolClientSetAttributes": true,
    "sharedId": "f3d70b73",
    "resourceName": "myrecipeslolAUTH",
    "authSelections": "userPoolOnly",
    "useDefault": "manual",
    "userPoolGroups": false,
    "adminQueries": true,
    "triggers": {},
    "hostedUI": true,
    "hostedUIDomainName": "myrecipeslol123",
    "authProvidersUserPool": [],
    "hostedUIProviderMeta": "[]",
    "oAuthMetadata": "{\"AllowedOAuthFlows\":[\"code\"],\"AllowedOAuthScopes\":[\"phone\",\"email\",\"openid\",\"profile\",\"aws.cognito.signin.user.admin\"],\"CallbackURLs\":[\"https://u7jfzire27.execute-api.us-west-1.amazonaws.com/test/example/?postID=5&number=7/\"],\"LogoutURLs\":[\"https://example.com/\"]}",
    "userPoolGroupList": [],
    "serviceName": "Cognito",
    "usernameCaseSensitive": false,
    "useEnabledMfas": true
  }
}